pyramid_basemodel/__init__.py
pyramid_basemodel/blob.py
pyramid_basemodel/container.py
pyramid_basemodel/interfaces.py
pyramid_basemodel/mixin.py
pyramid_basemodel/root.py
pyramid_basemodel/slug.py
pyramid_basemodel/tree.py
pyramid_basemodel/util.py
pyramid_basemodel-0.7.0.dist-info/METADATA
pyramid_basemodel-0.7.0.dist-info/WHEEL
pyramid_basemodel-0.7.0.dist-info/top_level.txt
pyramid_basemodel-0.7.0.dist-info/zip-safe
pyramid_basemodel-0.7.0.dist-info/RECORD
