Metadata-Version: 2.4
Name: pyramid_basemodel
Version: 0.7.0
Summary: pyramid_basemodel - a thin, low level SQLAlchemy bindings to pyramid
Author: James Arthur
Maintainer-email: Grzegorz Śliwiński <fizyk+pypi@fizyk.dev>
License: This is free and unencumbered software released into the public domain.
Project-URL: Source, https://github.com/fizyk/pyramid_basemodel/
Project-URL: Bug Tracker, https://github.com/fizyk/pyramid_basemodel/issues
Project-URL: Changelog, https://github.com/fizyk/pyramid_basemodel/blob/v0.7.0/CHANGES.rst
Keywords: pyramid,sqlalchemy
Classifier: Development Status :: 4 - Beta
Classifier: Environment :: Web Environment
Classifier: Intended Audience :: Developers
Classifier: License :: OSI Approved :: The Unlicense (Unlicense)
Classifier: Natural Language :: English
Classifier: Operating System :: OS Independent
Classifier: Programming Language :: Python
Classifier: Programming Language :: Python :: 3
Classifier: Programming Language :: Python :: 3.10
Classifier: Programming Language :: Python :: 3.11
Classifier: Programming Language :: Python :: 3.12
Classifier: Programming Language :: Python :: 3.13
Classifier: Programming Language :: Python :: 3.14
Classifier: Framework :: Pyramid
Classifier: Topic :: Database :: Front-Ends
Classifier: Topic :: Internet :: WWW/HTTP
Classifier: Topic :: Internet :: WWW/HTTP :: WSGI
Classifier: Topic :: Software Development :: Libraries :: Python Modules
Requires-Python: >=3.10
Requires-Dist: pyramid
Requires-Dist: pyramid_tm
Requires-Dist: requests
Requires-Dist: SQLAlchemy>=2
Requires-Dist: zope.interface
Requires-Dist: zope.sqlalchemy
Requires-Dist: python-slugify
Requires-Dist: inflect
